marshmallow_jsonschema/__init__.py
marshmallow_jsonschema/base.py
marshmallow_jsonschema/exceptions.py
marshmallow_jsonschema/validation.py
marshmallow_jsonschema/extensions/__init__.py
marshmallow_jsonschema/extensions/react_jsonschema_form.py
marshmallow_jsonschema-0.13.0.dist-info/LICENSE
marshmallow_jsonschema-0.13.0.dist-info/METADATA
marshmallow_jsonschema-0.13.0.dist-info/WHEEL
marshmallow_jsonschema-0.13.0.dist-info/top_level.txt
marshmallow_jsonschema-0.13.0.dist-info/RECORD
