Metadata-Version: 2.1
Name: marshmallow-jsonschema
Version: 0.13.0
Summary: JSON Schema Draft v7 (http://json-schema.org/) formatting with marshmallow
Home-page: https://github.com/fuhrysteve/marshmallow-jsonschema
Author: Stephen Fuhry
Author-email: fuhrysteve@gmail.com
License: MIT License
Keywords: marshmallow-jsonschema marshmallow schema serialization jsonschema validation
Platform: UNKNOWN
Classifier: Intended Audience :: Developers
Classifier: License :: OSI Approved :: MIT License
Classifier: Natural Language :: English
Classifier: Programming Language :: Python :: 3
Classifier: Programming Language :: Python :: 3.6
Classifier: Programming Language :: Python :: 3.7
Classifier: Programming Language :: Python :: 3.8
Classifier: Programming Language :: Python :: 3.9
Classifier: Programming Language :: Python :: 3.10
Requires-Python: >=3.6
Provides-Extra: enum
Provides-Extra: union
License-File: LICENSE
